CHANGELOG.md
LICENSE
MANIFEST.in
README.md
setup.cfg
setup.py
parm/.DS_Store
parm/__init__.py
parm/_compat.py
parm/commands.py
parm/markdown_writer.py
parm/md_ext.py
parm/mermaid_ext.py
parm/template.py
parm/utils.py
parm.egg-info/PKG-INFO
parm.egg-info/SOURCES.txt
parm.egg-info/dependency_links.txt
parm.egg-info/entry_points.txt
parm.egg-info/not-zip-safe
parm.egg-info/requires.txt
parm.egg-info/top_level.txt
parm/plugins/__init__.py
parm/templates/.DS_Store
parm/templates/env/.nojekyll
parm/templates/env/conf.py.txt
parm/templates/env/exclude.txt
parm/templates/env/index.md
parm/templates/env/introduction.md
parm/templates/theme/.DS_Store
parm/templates/theme/bootstrap/.DS_Store
parm/templates/theme/bootstrap/static/.DS_Store
parm/templates/theme/bootstrap/static/comment.js
parm/templates/theme/bootstrap/static/custom.css
parm/templates/theme/bootstrap/static/docs.css
parm/templates/theme/bootstrap/static/docs.js
parm/templates/theme/bootstrap/static/external-link-ltr-icon.png
parm/templates/theme/bootstrap/static/jquery.hotkeys.js
parm/templates/theme/bootstrap/static/jquery.min.js
parm/templates/theme/bootstrap/static/jquery.sticky-kit.min.js
parm/templates/theme/bootstrap/static/jquery.ui.totop.js
parm/templates/theme/bootstrap/static/parm.css
parm/templates/theme/bootstrap/static/ui.totop.css
parm/templates/theme/bootstrap/static/asset/html5.js
parm/templates/theme/bootstrap/static/asset/light.css
parm/templates/theme/bootstrap/static/asset/prettify.css
parm/templates/theme/bootstrap/static/asset/prettify.js
parm/templates/theme/bootstrap/static/asset/sons-of-obsidian.css
parm/templates/theme/bootstrap/static/asset/sunburst.css
parm/templates/theme/bootstrap/static/bootstrap/css/bootstrap.min.css
parm/templates/theme/bootstrap/static/bootstrap/fonts/glyphicons-halflings-regular.eot
parm/templates/theme/bootstrap/static/bootstrap/fonts/glyphicons-halflings-regular.svg
parm/templates/theme/bootstrap/static/bootstrap/fonts/glyphicons-halflings-regular.ttf
parm/templates/theme/bootstrap/static/bootstrap/fonts/glyphicons-halflings-regular.woff
parm/templates/theme/bootstrap/static/bootstrap/fonts/glyphicons-halflings-regular.woff2
