Metadata-Version: 1.1
Name: parm
Version: 1.11
Summary: Markdown to html convertor tool
Home-page: https://github.com/limodou/parm
Author: limodou
Author-email: limodou@gmail.com
License: BSD
Keywords: markdown convertor
Platform: any
Classifier: Development Status :: 2 - Pre-Alpha
Classifier: Intended Audience :: Developers
Classifier: License :: OSI Approved :: BSD License
Classifier: Programming Language :: Python
Classifier: Operating System :: OS Independent
Classifier: Programming Language :: Python :: 2.6
Classifier: Programming Language :: Python :: 2.7
Classifier: Programming Language :: Python :: 3.3
Classifier: Programming Language :: Python :: 3.4
